<?xml version="1.0" encoding="UTF-8"?>
<localReferenceApplication:LocalReferenceApplication xmlns:xsi="http://www.w3.org/2001/XMLSchema-instance"
    xmlns:localReferenceApplication="http://www.odcgroup.com/t24/application/localRefApplication/model/LocalReferenceApplication"
    xmlns:translationDsl="http://www.odcgroup.com/translation/TranslationDsl" forApplication="name://DE_Ticklers:EB_TICKLER#">
  <localField groupName="No" localRefID="ACTION.TYPE">
    <label xsi:type="translationDsl:LocalTranslations">
      <translations locale="en" text="ACTION.TYPE"/>
    </label>
    <toolTip xsi:type="translationDsl:LocalTranslations"/>
  </localField>
  <localField groupName="No" localRefID="TRANS.REFERENCE">
    <label xsi:type="translationDsl:LocalTranslations">
      <translations locale="en" text="TRANS.REFERECE"/>
    </label>
    <toolTip xsi:type="translationDsl:LocalTranslations"/>
  </localField>
  <localField groupName="No" localRefID="CUSTOMER.ID">
    <label xsi:type="translationDsl:LocalTranslations">
      <translations locale="en" text="CUSTOMER.ID"/>
    </label>
    <toolTip xsi:type="translationDsl:LocalTranslations"/>
  </localField>
</localReferenceApplication:LocalReferenceApplication>
