<?xml version="1.0" encoding="UTF-8"?>		
<Metadata ModelName="Prospect-models" Version="1.0" 
		xmlns="http://iris.temenos.com/metadata.xsd" 
		xmlns:xsi="http://www.w3.org/2001/XMLSchema-instance" 
		xsi:schemaLocation="http://iris.temenos.com metadata.xsd">
	<Entity Name="AcOneStopAcctOpen">
		<Property Name="DealNo">
			<Term Name="TERM_ID_FIELD">true</Term>
			<Term Name="TERM_MANDATORY">true</Term>
			<Term Name="TERM_SEMANTIC_TYPE">A</Term>
		</Property>
		<Property Name="Customer">
			<Term Name="TERM_MANDATORY">true</Term>
		</Property>
		<Property Name="CustomerIbuser" />
		<Property Name="SlSavingsAcc" />
		<Property Name="SlCurr">
			<Term Name="TERM_SEMANTIC_TYPE">CCY</Term>
		</Property>
		<Property Name="SlCardType">
			<Term Name="TERM_SEMANTIC_TYPE">A</Term>
		</Property>
		<Property Name="SlCardNumber" />
		<Property Name="SlPassbook" />
		<Property Name="SlChequeBook" />
		<Property Name="SlIbuser" />
		<Property Name="SlMbuser" />
		<Property Name="SlJointHolderMvGroup">
			<Term Name="TERM_LIST_TYPE">true</Term>
			<Property Name="valuePosition" />
			<Property Name="subValuePosition" />
			<Property Name="SlJointHolder">
				<Term Name="TERM_SEMANTIC_TYPE">CUS</Term>
			</Property>
			<Property Name="SlRelation">
				<Term Name="TERM_SEMANTIC_TYPE">A</Term>
			</Property>
			<Property Name="SlJointNotes" />
		</Property>
		<Property Name="SfSavingsAcc" />
		<Property Name="SfCurr">
			<Term Name="TERM_SEMANTIC_TYPE">CCY</Term>
		</Property>
		<Property Name="SfCardType">
			<Term Name="TERM_SEMANTIC_TYPE">A</Term>
		</Property>
		<Property Name="SfCardNumber" />
		<Property Name="SfPassbook" />
		<Property Name="SfChequeBook" />
		<Property Name="SfIbuser" />
		<Property Name="SfMbuser" />
		<Property Name="SfJointHolderMvGroup">
			<Term Name="TERM_LIST_TYPE">true</Term>
			<Property Name="valuePosition" />
			<Property Name="subValuePosition" />
			<Property Name="SfJointHolder">
				<Term Name="TERM_SEMANTIC_TYPE">CUS</Term>
			</Property>
			<Property Name="SfRelation">
				<Term Name="TERM_SEMANTIC_TYPE">A</Term>
			</Property>
			<Property Name="SfJointNotes" />
		</Property>
		<Property Name="ClCurrentAcc" />
		<Property Name="ClCurr">
			<Term Name="TERM_SEMANTIC_TYPE">CCY</Term>
		</Property>
		<Property Name="ClCardType">
			<Term Name="TERM_SEMANTIC_TYPE">A</Term>
		</Property>
		<Property Name="ClCardNumber" />
		<Property Name="ClChequeBook" />
		<Property Name="ClOverdraft" />
		<Property Name="ClOdAmount" />
		<Property Name="ClIbuser" />
		<Property Name="ClMbuser" />
		<Property Name="ClJointHolderMvGroup">
			<Term Name="TERM_LIST_TYPE">true</Term>
			<Property Name="valuePosition" />
			<Property Name="subValuePosition" />
			<Property Name="ClJointHolder">
				<Term Name="TERM_SEMANTIC_TYPE">CUS</Term>
			</Property>
			<Property Name="ClRelation">
				<Term Name="TERM_SEMANTIC_TYPE">A</Term>
			</Property>
			<Property Name="ClJointNotes" />
		</Property>
		<Property Name="CfCurrentAcc" />
		<Property Name="CfCurr">
			<Term Name="TERM_SEMANTIC_TYPE">CCY</Term>
		</Property>
		<Property Name="CfCardType">
			<Term Name="TERM_SEMANTIC_TYPE">A</Term>
		</Property>
		<Property Name="CfCardNumber" />
		<Property Name="CfChequeBook" />
		<Property Name="CfOverdraft" />
		<Property Name="CfOdAmount" />
		<Property Name="CfIbuser" />
		<Property Name="CfMbuser" />
		<Property Name="CfJointHolderMvGroup">
			<Term Name="TERM_LIST_TYPE">true</Term>
			<Property Name="valuePosition" />
			<Property Name="subValuePosition" />
			<Property Name="CfJointHolder">
				<Term Name="TERM_SEMANTIC_TYPE">CUS</Term>
			</Property>
			<Property Name="CfRelation">
				<Term Name="TERM_SEMANTIC_TYPE">A</Term>
			</Property>
			<Property Name="CfJointNotes" />
		</Property>
		<Property Name="FixedDeposit" />
		<Property Name="FdCurrency">
			<Term Name="TERM_SEMANTIC_TYPE">CCY</Term>
		</Property>
		<Property Name="FdProduct" />
		<Property Name="FdAmount" />
		<Property Name="FdStartDate" />
		<Property Name="FdMaturityDate" />
		<Property Name="FdDebitAccount">
			<Term Name="TERM_SEMANTIC_TYPE">ANT</Term>
		</Property>
		<Property Name="FdCreditAccount">
			<Term Name="TERM_SEMANTIC_TYPE">ANT</Term>
		</Property>
		<Property Name="FdIntCapt" />
		<Property Name="FdIntSchedule" />
		<Property Name="FdRollover" />
		<Property Name="FdRolloverTerm" />
		<Property Name="FdIbUser" />
		<Property Name="FdMbUser" />
		<Property Name="SlDepositType" />
		<Property Name="ClDepositType" />
		<Property Name="SfDepositType" />
		<Property Name="CfDepositType" />
		<Property Name="SlDepositAmount" />
		<Property Name="ClDepositAmount" />
		<Property Name="SfDepositAmount" />
		<Property Name="CfDepositAmount" />
		<Property Name="ReqForInfo" />
		<Property Name="SaIntCashdep" />
		<Property Name="CaIntCashdep" />
		<Property Name="FixdepIntCashdep" />
		<Property Name="OverrideMvGroup">
			<Term Name="TERM_LIST_TYPE">true</Term>
			<Property Name="valuePosition" />
			<Property Name="subValuePosition" />
			<Property Name="Override" />
		</Property>
		<Property Name="RecordStatus" />
		<Property Name="CurrNo" />
		<Property Name="InputterMvGroup">
			<Term Name="TERM_LIST_TYPE">true</Term>
			<Property Name="valuePosition" />
			<Property Name="subValuePosition" />
			<Property Name="Inputter" />
		</Property>
		<Property Name="DateTimeMvGroup">
			<Term Name="TERM_LIST_TYPE">true</Term>
			<Property Name="valuePosition" />
			<Property Name="subValuePosition" />
			<Property Name="DateTime" />
		</Property>
		<Property Name="Authoriser" />
		<Property Name="CoCode">
			<Term Name="TERM_SEMANTIC_TYPE">A</Term>
		</Property>
		<Property Name="DeptCode" />
		<Property Name="AuditorCode" />
		<Property Name="AuditDateTime" />
		<Property Name="Id" />
	</Entity>
</Metadata>
