<?xml version="1.0" encoding="UTF-8"?>		
<Metadata ModelName="Prospect-models" Version="1.0" 
		xmlns="http://iris.temenos.com/metadata.xsd" 
		xmlns:xsi="http://www.w3.org/2001/XMLSchema-instance" 
		xsi:schemaLocation="http://iris.temenos.com metadata.xsd">
	<Entity Name="MdSchedules">
		<Property Name="DealDate">
			<Term Name="TERM_ID_FIELD">true</Term>
			<Term Name="TERM_MANDATORY">true</Term>
			<Term Name="TERM_SEMANTIC_TYPE">A</Term>
		</Property>
		<Property Name="ChargeSch">
			<Term Name="TERM_SEMANTIC_TYPE">A</Term>
		</Property>
		<Property Name="ChargeAdvice" />
		<Property Name="PrincipalSch">
			<Term Name="TERM_SEMANTIC_TYPE">A</Term>
		</Property>
		<Property Name="MaturitySch">
			<Term Name="TERM_SEMANTIC_TYPE">A</Term>
		</Property>
		<Property Name="CommissionSch">
			<Term Name="TERM_SEMANTIC_TYPE">A</Term>
		</Property>
		<Property Name="ProvRelSch">
			<Term Name="TERM_SEMANTIC_TYPE">A</Term>
		</Property>
		<Property Name="RateChgSch">
			<Term Name="TERM_SEMANTIC_TYPE">A</Term>
		</Property>
		<Property Name="AdvExpSch">
			<Term Name="TERM_SEMANTIC_TYPE">A</Term>
		</Property>
		<Property Name="Id" />
	</Entity>
</Metadata>
