<?xml version="1.0" encoding="UTF-8"?>		
<Metadata ModelName="Prospect-models" Version="1.0" 
		xmlns="http://iris.temenos.com/metadata.xsd" 
		xmlns:xsi="http://www.w3.org/2001/XMLSchema-instance" 
		xsi:schemaLocation="http://iris.temenos.com metadata.xsd">
	<Entity Name="ReDealBalances">
		<Property Name="DealBalId">
			<Term Name="TERM_ID_FIELD">true</Term>
			<Term Name="TERM_MANDATORY">true</Term>
			<Term Name="TERM_SEMANTIC_TYPE">A</Term>
		</Property>
		<Property Name="NarrMvGroup">
			<Term Name="TERM_LIST_TYPE">true</Term>
			<Property Name="valuePosition" />
			<Property Name="subValuePosition" />
			<Property Name="NarrSvGroup">
				<Term Name="TERM_LIST_TYPE">true</Term>
				<Term Name="TERM_LANG_TYPE">true</Term>
				<Property Name="valuePosition" />
				<Property Name="subValuePosition" />
				<Property Name="LanguageCode" />
				<Property Name="Narr" />
			</Property>
		</Property>
		<Property Name="ContractNo" />
		<Property Name="CustTitle" />
		<Property Name="CurrencyMvGroup">
			<Term Name="TERM_LIST_TYPE">true</Term>
			<Property Name="valuePosition" />
			<Property Name="subValuePosition" />
			<Property Name="Currency">
				<Term Name="TERM_SEMANTIC_TYPE">CCY</Term>
			</Property>
		</Property>
		<Property Name="CcyAmount" />
		<Property Name="LcyAmount" />
		<Property Name="IntRate" />
		<Property Name="ValueDate" />
		<Property Name="MatDate" />
		<Property Name="IntBasis" />
		<Property Name="ConKeyTypeMvGroup">
			<Term Name="TERM_LIST_TYPE">true</Term>
			<Property Name="valuePosition" />
			<Property Name="subValuePosition" />
			<Property Name="ConKeyType" />
			<Property Name="ConCcyAmt" />
			<Property Name="DealCcyAmt" />
		</Property>
		<Property Name="Id" />
	</Entity>
</Metadata>
