<?xml version="1.0" encoding="UTF-8"?>		
<Metadata ModelName="Prospect-models" Version="1.0" 
		xmlns="http://iris.temenos.com/metadata.xsd" 
		xmlns:xsi="http://www.w3.org/2001/XMLSchema-instance" 
		xsi:schemaLocation="http://iris.temenos.com metadata.xsd">
	<Entity Name="BrParameter">
		<Property Name="Key">
			<Term Name="TERM_ID_FIELD">true</Term>
			<Term Name="TERM_MANDATORY">true</Term>
		</Property>
		<Property Name="CentralSerName" />
		<Property Name="CentralSerAdd" />
		<Property Name="BrDbLocationMvGroup">
			<Term Name="TERM_LIST_TYPE">true</Term>
			<Property Name="valuePosition" />
			<Property Name="subValuePosition" />
			<Property Name="BrDbLocation" />
		</Property>
		<Property Name="ExcludeFilesMvGroup">
			<Term Name="TERM_LIST_TYPE">true</Term>
			<Property Name="valuePosition" />
			<Property Name="subValuePosition" />
			<Property Name="ExcludeFiles">
				<Term Name="TERM_SEMANTIC_TYPE">A</Term>
			</Property>
		</Property>
		<Property Name="ClearFilesMvGroup">
			<Term Name="TERM_LIST_TYPE">true</Term>
			<Property Name="valuePosition" />
			<Property Name="subValuePosition" />
			<Property Name="ClearFiles">
				<Term Name="TERM_SEMANTIC_TYPE">A</Term>
			</Property>
		</Property>
		<Property Name="StaticAppsMvGroup">
			<Term Name="TERM_LIST_TYPE">true</Term>
			<Property Name="valuePosition" />
			<Property Name="subValuePosition" />
			<Property Name="StaticApps">
				<Term Name="TERM_SEMANTIC_TYPE">A</Term>
			</Property>
		</Property>
		<Property Name="OfflnApsAllwdMvGroup">
			<Term Name="TERM_LIST_TYPE">true</Term>
			<Property Name="valuePosition" />
			<Property Name="subValuePosition" />
			<Property Name="OfflnApsAllwd">
				<Term Name="TERM_SEMANTIC_TYPE">A</Term>
			</Property>
		</Property>
		<Property Name="OfflnApsUpldMvGroup">
			<Term Name="TERM_LIST_TYPE">true</Term>
			<Property Name="valuePosition" />
			<Property Name="subValuePosition" />
			<Property Name="OfflnApsUpld" />
		</Property>
		<Property Name="SfqOfsSourceId">
			<Term Name="TERM_MANDATORY">true</Term>
			<Term Name="TERM_SEMANTIC_TYPE">A</Term>
		</Property>
		<Property Name="MonitorPort">
			<Term Name="TERM_MANDATORY">true</Term>
		</Property>
		<Property Name="MaxEntPerFile" />
		<Property Name="ExpAccBalLoc">
			<Term Name="TERM_MANDATORY">true</Term>
		</Property>
		<Property Name="ExpStaAppLoc">
			<Term Name="TERM_MANDATORY">true</Term>
		</Property>
		<Property Name="RecIncFileMvGroup">
			<Term Name="TERM_LIST_TYPE">true</Term>
			<Property Name="valuePosition" />
			<Property Name="subValuePosition" />
			<Property Name="RecIncFile" />
			<Property Name="RecIncIdSvGroup">
				<Term Name="TERM_LIST_TYPE">true</Term>
				<Property Name="valuePosition" />
				<Property Name="subValuePosition" />
				<Property Name="RecIncId" />
			</Property>
		</Property>
		<Property Name="Reserved5" />
		<Property Name="Reserved6" />
		<Property Name="Reserved7" />
		<Property Name="Reserved8" />
		<Property Name="Reserved9" />
		<Property Name="Reserved10" />
		<Property Name="OverrideMvGroup">
			<Term Name="TERM_LIST_TYPE">true</Term>
			<Property Name="valuePosition" />
			<Property Name="subValuePosition" />
			<Property Name="Override" />
		</Property>
		<Property Name="RecordStatus" />
		<Property Name="CurrNo" />
		<Property Name="InputterMvGroup">
			<Term Name="TERM_LIST_TYPE">true</Term>
			<Property Name="valuePosition" />
			<Property Name="subValuePosition" />
			<Property Name="Inputter" />
		</Property>
		<Property Name="DateTimeMvGroup">
			<Term Name="TERM_LIST_TYPE">true</Term>
			<Property Name="valuePosition" />
			<Property Name="subValuePosition" />
			<Property Name="DateTime" />
		</Property>
		<Property Name="Authoriser" />
		<Property Name="CoCode">
			<Term Name="TERM_SEMANTIC_TYPE">A</Term>
		</Property>
		<Property Name="DeptCode" />
		<Property Name="AuditorCode" />
		<Property Name="AuditDateTime" />
		<Property Name="Id" />
	</Entity>
</Metadata>
