<?xml version="1.0" encoding="UTF-8"?>		
<Metadata ModelName="Prospect-models" Version="1.0" 
		xmlns="http://iris.temenos.com/metadata.xsd" 
		xmlns:xsi="http://www.w3.org/2001/XMLSchema-instance" 
		xsi:schemaLocation="http://iris.temenos.com metadata.xsd">
	<Entity Name="ScAssetBalPosted">
		<Property Name="AssetBalPostedKey">
			<Term Name="TERM_ID_FIELD">true</Term>
			<Term Name="TERM_MANDATORY">true</Term>
			<Term Name="TERM_SEMANTIC_TYPE">A</Term>
		</Property>
		<Property Name="Customer">
			<Term Name="TERM_SEMANTIC_TYPE">CUS</Term>
		</Property>
		<Property Name="ReferenceCcy">
			<Term Name="TERM_MANDATORY">true</Term>
			<Term Name="TERM_SEMANTIC_TYPE">CCY</Term>
		</Property>
		<Property Name="ExtDateMvGroup">
			<Term Name="TERM_LIST_TYPE">true</Term>
			<Property Name="valuePosition" />
			<Property Name="subValuePosition" />
			<Property Name="ExtDate">
				<Term Name="TERM_MANDATORY">true</Term>
			</Property>
			<Property Name="SubAstTypeSvGroup">
				<Term Name="TERM_LIST_TYPE">true</Term>
				<Property Name="valuePosition" />
				<Property Name="subValuePosition" />
				<Property Name="SubAstType">
					<Term Name="TERM_MANDATORY">true</Term>
					<Term Name="TERM_SEMANTIC_TYPE">A</Term>
				</Property>
				<Property Name="Nominal">
					<Term Name="TERM_MANDATORY">true</Term>
				</Property>
				<Property Name="NominalLcy">
					<Term Name="TERM_MANDATORY">true</Term>
				</Property>
				<Property Name="AssetBal">
					<Term Name="TERM_MANDATORY">true</Term>
				</Property>
				<Property Name="AstBalScy">
					<Term Name="TERM_MANDATORY">true</Term>
				</Property>
				<Property Name="SecurityCcy">
					<Term Name="TERM_MANDATORY">true</Term>
					<Term Name="TERM_SEMANTIC_TYPE">CCY</Term>
				</Property>
				<Property Name="Product">
					<Term Name="TERM_MANDATORY">true</Term>
					<Term Name="TERM_SEMANTIC_TYPE">A</Term>
				</Property>
				<Property Name="AssetId" />
				<Property Name="SvRes3" />
				<Property Name="SvRes2" />
				<Property Name="SvRes1" />
			</Property>
			<Property Name="TotAssetBal" />
			<Property Name="TotAvgNominal" />
			<Property Name="TotAvgNomLcy" />
			<Property Name="TotAvgAstBal" />
			<Property Name="TotAstBalScy" />
			<Property Name="TotAvAsBlSc" />
			<Property Name="MvRes5" />
			<Property Name="MvRes4" />
			<Property Name="MvRes3" />
			<Property Name="MvRes2" />
			<Property Name="MvRes1" />
		</Property>
		<Property Name="Portfolio">
			<Term Name="TERM_SEMANTIC_TYPE">SAM</Term>
		</Property>
		<Property Name="SecurityCode">
			<Term Name="TERM_SEMANTIC_TYPE">ANY</Term>
		</Property>
		<Property Name="Reserved5" />
		<Property Name="Reserved4" />
		<Property Name="Reserved3" />
		<Property Name="Reserved2" />
		<Property Name="Reserved1" />
		<Property Name="RecordStatus" />
		<Property Name="CurrNo" />
		<Property Name="InputterMvGroup">
			<Term Name="TERM_LIST_TYPE">true</Term>
			<Property Name="valuePosition" />
			<Property Name="subValuePosition" />
			<Property Name="Inputter" />
		</Property>
		<Property Name="DateTimeMvGroup">
			<Term Name="TERM_LIST_TYPE">true</Term>
			<Property Name="valuePosition" />
			<Property Name="subValuePosition" />
			<Property Name="DateTime" />
		</Property>
		<Property Name="Authoriser" />
		<Property Name="CoCode">
			<Term Name="TERM_SEMANTIC_TYPE">A</Term>
		</Property>
		<Property Name="DeptCode" />
		<Property Name="AuditorCode" />
		<Property Name="AuditDateTime" />
		<Property Name="Id" />
	</Entity>
</Metadata>
