<?xml version="1.0" encoding="UTF-8"?>		
<Metadata ModelName="Prospect-models" Version="1.0" 
		xmlns="http://iris.temenos.com/metadata.xsd" 
		xmlns:xsi="http://www.w3.org/2001/XMLSchema-instance" 
		xsi:schemaLocation="http://iris.temenos.com metadata.xsd">
	<Entity Name="AaArrangement">
		<Property Name="ArrangementId">
			<Term Name="TERM_ID_FIELD">true</Term>
			<Term Name="TERM_MANDATORY">true</Term>
			<Term Name="TERM_SEMANTIC_TYPE">ARR</Term>
		</Property>
		<Property Name="Customer">
			<Term Name="TERM_SEMANTIC_TYPE">CUS</Term>
		</Property>
		<Property Name="OwnerMvGroup">
			<Term Name="TERM_LIST_TYPE">true</Term>
			<Property Name="valuePosition" />
			<Property Name="subValuePosition" />
			<Property Name="Owner">
				<Term Name="TERM_SEMANTIC_TYPE">CUS</Term>
			</Property>
		</Property>
		<Property Name="Currency">
			<Term Name="TERM_SEMANTIC_TYPE">A</Term>
		</Property>
		<Property Name="CoCode">
			<Term Name="TERM_SEMANTIC_TYPE">COM</Term>
		</Property>
		<Property Name="Channel" />
		<Property Name="ArrStatus" />
		<Property Name="StartDate" />
		<Property Name="LinkedApplMvGroup">
			<Term Name="TERM_LIST_TYPE">true</Term>
			<Property Name="valuePosition" />
			<Property Name="subValuePosition" />
			<Property Name="LinkedAppl" />
			<Property Name="LinkedApplId" />
		</Property>
		<Property Name="ProductLine">
			<Term Name="TERM_SEMANTIC_TYPE">A</Term>
		</Property>
		<Property Name="ProductGroup">
			<Term Name="TERM_SEMANTIC_TYPE">A</Term>
		</Property>
		<Property Name="ProductMvGroup">
			<Term Name="TERM_LIST_TYPE">true</Term>
			<Property Name="valuePosition" />
			<Property Name="subValuePosition" />
			<Property Name="Product">
				<Term Name="TERM_SEMANTIC_TYPE">A</Term>
			</Property>
			<Property Name="ProdEffDate" />
			<Property Name="ProductStatus" />
			<Property Name="PropertySvGroup">
				<Term Name="TERM_LIST_TYPE">true</Term>
				<Property Name="valuePosition" />
				<Property Name="subValuePosition" />
				<Property Name="Property">
					<Term Name="TERM_SEMANTIC_TYPE">A</Term>
				</Property>
			</Property>
			<Property Name="VariationEffDateSvGroup">
				<Term Name="TERM_LIST_TYPE">true</Term>
				<Property Name="valuePosition" />
				<Property Name="subValuePosition" />
				<Property Name="VariationEffDate" />
				<Property Name="Variation" />
			</Property>
		</Property>
		<Property Name="OrigContractDate" />
		<Property Name="LinkDateMvGroup">
			<Term Name="TERM_LIST_TYPE">true</Term>
			<Property Name="valuePosition" />
			<Property Name="subValuePosition" />
			<Property Name="LinkDate" />
			<Property Name="LinkTypeSvGroup">
				<Term Name="TERM_LIST_TYPE">true</Term>
				<Property Name="valuePosition" />
				<Property Name="subValuePosition" />
				<Property Name="LinkType" />
				<Property Name="LinkArrangement" />
				<Property Name="LinkProperty" />
			</Property>
			<Property Name="ArrangementType" />
		</Property>
		<Property Name="RelationshipDateMvGroup">
			<Term Name="TERM_LIST_TYPE">true</Term>
			<Property Name="valuePosition" />
			<Property Name="subValuePosition" />
			<Property Name="RelationshipDate" />
			<Property Name="RelationshipPlan" />
			<Property Name="RelationshipArr" />
			<Property Name="Reserved5" />
			<Property Name="Reserved4" />
		</Property>
		<Property Name="EligibilityReview" />
		<Property Name="LastReviewDateMvGroup">
			<Term Name="TERM_LIST_TYPE">true</Term>
			<Property Name="valuePosition" />
			<Property Name="subValuePosition" />
			<Property Name="LastReviewDate" />
		</Property>
		<Property Name="AgentId">
			<Term Name="TERM_SEMANTIC_TYPE">CUS</Term>
		</Property>
		<Property Name="AgentArrId">
			<Term Name="TERM_SEMANTIC_TYPE">ARR</Term>
		</Property>
		<Property Name="Id" />
	</Entity>
</Metadata>
