<?xml version="1.0" encoding="UTF-8"?>		
<Metadata ModelName="Prospect-models" Version="1.0" 
		xmlns="http://iris.temenos.com/metadata.xsd" 
		xmlns:xsi="http://www.w3.org/2001/XMLSchema-instance" 
		xsi:schemaLocation="http://iris.temenos.com metadata.xsd">
	<Entity Name="LetterOfCredit">
		<Property Name="LcNumber">
			<Term Name="TERM_ID_FIELD">true</Term>
			<Term Name="TERM_MANDATORY">true</Term>
			<Term Name="TERM_SEMANTIC_TYPE">LETT</Term>
		</Property>
		<Property Name="Operation">
			<Term Name="TERM_MANDATORY">true</Term>
		</Property>
		<Property Name="LcType">
			<Term Name="TERM_MANDATORY">true</Term>
			<Term Name="TERM_SEMANTIC_TYPE">A</Term>
		</Property>
		<Property Name="ExternalReference" />
		<Property Name="Revocable" />
		<Property Name="UcpInd" />
		<Property Name="IssuingBankNo">
			<Term Name="TERM_SEMANTIC_TYPE">CUS</Term>
		</Property>
		<Property Name="IssuingBankMvGroup">
			<Term Name="TERM_LIST_TYPE">true</Term>
			<Property Name="valuePosition" />
			<Property Name="subValuePosition" />
			<Property Name="IssuingBank" />
		</Property>
		<Property Name="IssuingBankAcc">
			<Term Name="TERM_SEMANTIC_TYPE">ACC</Term>
		</Property>
		<Property Name="ApplicantCustno">
			<Term Name="TERM_SEMANTIC_TYPE">CUS</Term>
		</Property>
		<Property Name="ApplicantMvGroup">
			<Term Name="TERM_LIST_TYPE">true</Term>
			<Property Name="valuePosition" />
			<Property Name="subValuePosition" />
			<Property Name="Applicant" />
		</Property>
		<Property Name="ApplicantAcc">
			<Term Name="TERM_SEMANTIC_TYPE">ACC</Term>
		</Property>
		<Property Name="BeneficiaryCustno">
			<Term Name="TERM_SEMANTIC_TYPE">CUS</Term>
		</Property>
		<Property Name="BeneficiaryMvGroup">
			<Term Name="TERM_LIST_TYPE">true</Term>
			<Property Name="valuePosition" />
			<Property Name="subValuePosition" />
			<Property Name="Beneficiary" />
		</Property>
		<Property Name="BeneficiaryAcc">
			<Term Name="TERM_SEMANTIC_TYPE">ACC</Term>
		</Property>
		<Property Name="AdvisingBkCustno">
			<Term Name="TERM_SEMANTIC_TYPE">CUS</Term>
		</Property>
		<Property Name="AdvisingBkMvGroup">
			<Term Name="TERM_LIST_TYPE">true</Term>
			<Property Name="valuePosition" />
			<Property Name="subValuePosition" />
			<Property Name="AdvisingBk" />
		</Property>
		<Property Name="AdvisingBkAcc">
			<Term Name="TERM_SEMANTIC_TYPE">ACC</Term>
		</Property>
		<Property Name="ConCusLink">
			<Term Name="TERM_SEMANTIC_TYPE">CUS</Term>
		</Property>
		<Property Name="ChargesAccount">
			<Term Name="TERM_SEMANTIC_TYPE">ALL</Term>
		</Property>
		<Property Name="LcCurrency">
			<Term Name="TERM_MANDATORY">true</Term>
			<Term Name="TERM_SEMANTIC_TYPE">CCY</Term>
		</Property>
		<Property Name="LcAmount">
			<Term Name="TERM_MANDATORY">true</Term>
		</Property>
		<Property Name="DayBasis" />
		<Property Name="DraftPrint" />
		<Property Name="CurrencyMarket">
			<Term Name="TERM_SEMANTIC_TYPE">DEF</Term>
		</Property>
		<Property Name="PositionType">
			<Term Name="TERM_SEMANTIC_TYPE">DEF</Term>
		</Property>
		<Property Name="LimitReference" />
		<Property Name="IssueDate" />
		<Property Name="ExpiryDate" />
		<Property Name="ExpiryPlace" />
		<Property Name="ClosingDate" />
		<Property Name="Tenor" />
		<Property Name="Days" />
		<Property Name="DateAccepted" />
		<Property Name="ParentLcNo">
			<Term Name="TERM_SEMANTIC_TYPE">LETT</Term>
		</Property>
		<Property Name="TransferredLcMvGroup">
			<Term Name="TERM_LIST_TYPE">true</Term>
			<Property Name="valuePosition" />
			<Property Name="subValuePosition" />
			<Property Name="TransferredLc" />
			<Property Name="TranPortAmt" />
		</Property>
		<Property Name="TrReimCustno">
			<Term Name="TERM_SEMANTIC_TYPE">CUS</Term>
		</Property>
		<Property Name="TrReimbAddrMvGroup">
			<Term Name="TERM_LIST_TYPE">true</Term>
			<Property Name="valuePosition" />
			<Property Name="subValuePosition" />
			<Property Name="TrReimbAddr" />
		</Property>
		<Property Name="TrReimAcct">
			<Term Name="TERM_SEMANTIC_TYPE">ACC</Term>
		</Property>
		<Property Name="ReimInfoMvGroup">
			<Term Name="TERM_LIST_TYPE">true</Term>
			<Property Name="valuePosition" />
			<Property Name="subValuePosition" />
			<Property Name="ReimInfo" />
		</Property>
		<Property Name="ReimReference" />
		<Property Name="PartShipments" />
		<Property Name="Transshipments" />
		<Property Name="ThirdPartyCustno">
			<Term Name="TERM_SEMANTIC_TYPE">CUS</Term>
		</Property>
		<Property Name="ThirdPartyMvGroup">
			<Term Name="TERM_LIST_TYPE">true</Term>
			<Property Name="valuePosition" />
			<Property Name="subValuePosition" />
			<Property Name="ThirdParty" />
		</Property>
		<Property Name="ThirdPartyAcc" />
		<Property Name="AdviseThruCustno">
			<Term Name="TERM_SEMANTIC_TYPE">CUS</Term>
		</Property>
		<Property Name="AdviseThruMvGroup">
			<Term Name="TERM_LIST_TYPE">true</Term>
			<Property Name="valuePosition" />
			<Property Name="subValuePosition" />
			<Property Name="AdviseThru" />
		</Property>
		<Property Name="AdviseThruAcc">
			<Term Name="TERM_SEMANTIC_TYPE">ACC</Term>
		</Property>
		<Property Name="RelatedLcNo">
			<Term Name="TERM_SEMANTIC_TYPE">A</Term>
		</Property>
		<Property Name="PercentageDrAmt" />
		<Property Name="PercentageCrAmt" />
		<Property Name="MaximumCrAmt" />
		<Property Name="AddAmtCoveredMvGroup">
			<Term Name="TERM_LIST_TYPE">true</Term>
			<Property Name="valuePosition" />
			<Property Name="subValuePosition" />
			<Property Name="AddAmtCovered" />
		</Property>
		<Property Name="AvailWithCustno">
			<Term Name="TERM_SEMANTIC_TYPE">CUS</Term>
		</Property>
		<Property Name="AvailableWithMvGroup">
			<Term Name="TERM_LIST_TYPE">true</Term>
			<Property Name="valuePosition" />
			<Property Name="subValuePosition" />
			<Property Name="AvailableWith" />
		</Property>
		<Property Name="DraftsAtMvGroup">
			<Term Name="TERM_LIST_TYPE">true</Term>
			<Property Name="valuePosition" />
			<Property Name="subValuePosition" />
			<Property Name="DraftsAt" />
		</Property>
		<Property Name="DraweeCustNo">
			<Term Name="TERM_SEMANTIC_TYPE">CUS</Term>
		</Property>
		<Property Name="DraweeMvGroup">
			<Term Name="TERM_LIST_TYPE">true</Term>
			<Property Name="valuePosition" />
			<Property Name="subValuePosition" />
			<Property Name="Drawee" />
		</Property>
		<Property Name="NarrativeChrgsMvGroup">
			<Term Name="TERM_LIST_TYPE">true</Term>
			<Property Name="valuePosition" />
			<Property Name="subValuePosition" />
			<Property Name="NarrativeChrgs" />
		</Property>
		<Property Name="PresentPeriodMvGroup">
			<Term Name="TERM_LIST_TYPE">true</Term>
			<Property Name="valuePosition" />
			<Property Name="subValuePosition" />
			<Property Name="PresentPeriod" />
		</Property>
		<Property Name="ConfirmInst" />
		<Property Name="DrawTypeMvGroup">
			<Term Name="TERM_LIST_TYPE">true</Term>
			<Property Name="valuePosition" />
			<Property Name="subValuePosition" />
			<Property Name="DrawType" />
			<Property Name="PaymentPct" />
			<Property Name="PayPortion" />
			<Property Name="AcptTmBand" />
			<Property Name="AddCoveredAmt" />
			<Property Name="PortionNo" />
			<Property Name="DrawingAmt" />
			<Property Name="ProOsAmt" />
			<Property Name="ProAwaitAmt" />
			<Property Name="LiabPortAmt" />
			<Property Name="LcyPortAmt" />
			<Property Name="PortLimRef" />
			<Property Name="PortOverdraw" />
			<Property Name="PortTrfAmt" />
			<Property Name="PortCumTrf" />
		</Property>
		<Property Name="MixedPaymentMvGroup">
			<Term Name="TERM_LIST_TYPE">true</Term>
			<Property Name="valuePosition" />
			<Property Name="subValuePosition" />
			<Property Name="MixedPayment" />
		</Property>
		<Property Name="DeferredPayMvGroup">
			<Term Name="TERM_LIST_TYPE">true</Term>
			<Property Name="valuePosition" />
			<Property Name="subValuePosition" />
			<Property Name="DeferredPay" />
		</Property>
		<Property Name="ShipDespatch" />
		<Property Name="OtherDespatchDet" />
		<Property Name="Transportation" />
		<Property Name="FinalDestination" />
		<Property Name="LatestShipment" />
		<Property Name="ShipmentPeriodMvGroup">
			<Term Name="TERM_LIST_TYPE">true</Term>
			<Property Name="valuePosition" />
			<Property Name="subValuePosition" />
			<Property Name="ShipmentPeriod" />
		</Property>
		<Property Name="DocumentCodeMvGroup">
			<Term Name="TERM_LIST_TYPE">true</Term>
			<Property Name="valuePosition" />
			<Property Name="subValuePosition" />
			<Property Name="DocumentCode" />
			<Property Name="Doc1stCopies" />
			<Property Name="Doc2ndCopies" />
			<Property Name="DocumentTxtSvGroup">
				<Term Name="TERM_LIST_TYPE">true</Term>
				<Property Name="valuePosition" />
				<Property Name="subValuePosition" />
				<Property Name="DocumentTxt" />
			</Property>
		</Property>
		<Property Name="ReimburseFrom" />
		<Property Name="ChargesFrom" />
		<Property Name="CategoryCode" />
		<Property Name="AccountOfficer">
			<Term Name="TERM_SEMANTIC_TYPE">DEF</Term>
		</Property>
		<Property Name="OtherOfficerMvGroup">
			<Term Name="TERM_LIST_TYPE">true</Term>
			<Property Name="valuePosition" />
			<Property Name="subValuePosition" />
			<Property Name="OtherOfficer" />
		</Property>
		<Property Name="BankToBankMvGroup">
			<Term Name="TERM_LIST_TYPE">true</Term>
			<Property Name="valuePosition" />
			<Property Name="subValuePosition" />
			<Property Name="BankToBank" />
		</Property>
		<Property Name="WaiveCharges" />
		<Property Name="ChargeCodeMvGroup">
			<Term Name="TERM_LIST_TYPE">true</Term>
			<Property Name="valuePosition" />
			<Property Name="subValuePosition" />
			<Property Name="ChargeCode" />
			<Property Name="ChargeAcct">
				<Term Name="TERM_SEMANTIC_TYPE">ALL</Term>
			</Property>
			<Property Name="ChargePctRate" />
			<Property Name="ChargePeriod" />
			<Property Name="ChargeCurrency">
				<Term Name="TERM_SEMANTIC_TYPE">CCY</Term>
			</Property>
			<Property Name="ChargeXchg" />
			<Property Name="ChargeAmount" />
			<Property Name="PartyCharged" />
			<Property Name="AmortCharges" />
			<Property Name="RelatedDrawing" />
			<Property Name="ChargeLccyAmt" />
			<Property Name="ChargeAccAmt" />
			<Property Name="ChargeStatus" />
			<Property Name="ChargeDate" />
		</Property>
		<Property Name="TaxCodeMvGroup">
			<Term Name="TERM_LIST_TYPE">true</Term>
			<Property Name="valuePosition" />
			<Property Name="subValuePosition" />
			<Property Name="TaxCode">
				<Term Name="TERM_SEMANTIC_TYPE">A</Term>
			</Property>
			<Property Name="TaxCcy">
				<Term Name="TERM_SEMANTIC_TYPE">CCY</Term>
			</Property>
			<Property Name="TaxAmt" />
			<Property Name="TaxParty" />
			<Property Name="TaxRelDrg" />
			<Property Name="TaxLccyAmt" />
			<Property Name="TaxAccAmt" />
			<Property Name="TaxChgSt" />
			<Property Name="TaxDrAcct">
				<Term Name="TERM_SEMANTIC_TYPE">ACC</Term>
			</Property>
			<Property Name="ChgCode" />
			<Property Name="TaxDate" />
		</Property>
		<Property Name="WpFile" />
		<Property Name="DescGoodsMvGroup">
			<Term Name="TERM_LIST_TYPE">true</Term>
			<Property Name="valuePosition" />
			<Property Name="subValuePosition" />
			<Property Name="DescGoods" />
		</Property>
		<Property Name="DocumentsReqMvGroup">
			<Term Name="TERM_LIST_TYPE">true</Term>
			<Property Name="valuePosition" />
			<Property Name="subValuePosition" />
			<Property Name="DocumentsReq" />
		</Property>
		<Property Name="AdditionlCondsMvGroup">
			<Term Name="TERM_LIST_TYPE">true</Term>
			<Property Name="valuePosition" />
			<Property Name="subValuePosition" />
			<Property Name="AdditionlConds" />
		</Property>
		<Property Name="InstructionsMvGroup">
			<Term Name="TERM_LIST_TYPE">true</Term>
			<Property Name="valuePosition" />
			<Property Name="subValuePosition" />
			<Property Name="Instructions" />
		</Property>
		<Property Name="NarrativeMvGroup">
			<Term Name="TERM_LIST_TYPE">true</Term>
			<Property Name="valuePosition" />
			<Property Name="subValuePosition" />
			<Property Name="NarrativeSvGroup">
				<Term Name="TERM_LIST_TYPE">true</Term>
				<Property Name="valuePosition" />
				<Property Name="subValuePosition" />
				<Property Name="Narrative" />
			</Property>
		</Property>
		<Property Name="AmendmentsMvGroup">
			<Term Name="TERM_LIST_TYPE">true</Term>
			<Property Name="valuePosition" />
			<Property Name="subValuePosition" />
			<Property Name="Amendments" />
		</Property>
		<Property Name="BookingDate" />
		<Property Name="ConfirmComm" />
		<Property Name="ConPartyChg" />
		<Property Name="OpeningComm" />
		<Property Name="OpnPartyChg" />
		<Property Name="FullyUtilised" />
		<Property Name="AwaitingMt701" />
		<Property Name="OldLcNumber" />
		<Property Name="AdviseThurRef" />
		<Property Name="AmendmentNo" />
		<Property Name="AmendmentDte" />
		<Property Name="AmendmentDel" />
		<Property Name="IssueBkKeyed" />
		<Property Name="BackToBack" />
		<Property Name="Provision" />
		<Property Name="RelProvis" />
		<Property Name="ProvisAcc">
			<Term Name="TERM_SEMANTIC_TYPE">ANT</Term>
		</Property>
		<Property Name="DbProvAmount" />
		<Property Name="ProvisPercent" />
		<Property Name="ProvExchRate" />
		<Property Name="ProvisAmount" />
		<Property Name="ProOutAmount" />
		<Property Name="ProAwaitRel" />
		<Property Name="ProvisionRate" />
		<Property Name="BankToBk740MvGroup">
			<Term Name="TERM_LIST_TYPE">true</Term>
			<Property Name="valuePosition" />
			<Property Name="subValuePosition" />
			<Property Name="BankToBk740" />
		</Property>
		<Property Name="OverdrawnAmt" />
		<Property Name="BrokerPercent" />
		<Property Name="ClausesTextMvGroup">
			<Term Name="TERM_LIST_TYPE">true</Term>
			<Property Name="valuePosition" />
			<Property Name="subValuePosition" />
			<Property Name="ClausesTextSvGroup">
				<Term Name="TERM_LIST_TYPE">true</Term>
				<Property Name="valuePosition" />
				<Property Name="subValuePosition" />
				<Property Name="ClausesText" />
			</Property>
		</Property>
		<Property Name="PortNoBen" />
		<Property Name="NegDealerRefno" />
		<Property Name="PortNoAppIss" />
		<Property Name="CreditProvisAcc">
			<Term Name="TERM_SEMANTIC_TYPE">ANT</Term>
		</Property>
		<Property Name="AdviceExpiryDate" />
		<Property Name="AssnReferenceMvGroup">
			<Term Name="TERM_LIST_TYPE">true</Term>
			<Property Name="valuePosition" />
			<Property Name="subValuePosition" />
			<Property Name="AssnReference" />
			<Property Name="AssnCustno">
				<Term Name="TERM_SEMANTIC_TYPE">CUS</Term>
			</Property>
			<Property Name="AssnAddSvGroup">
				<Term Name="TERM_LIST_TYPE">true</Term>
				<Property Name="valuePosition" />
				<Property Name="subValuePosition" />
				<Property Name="AssnAdd" />
			</Property>
			<Property Name="AssnAmount" />
			<Property Name="AssnOsAmt" />
			<Property Name="AssnNoteSvGroup">
				<Term Name="TERM_LIST_TYPE">true</Term>
				<Property Name="valuePosition" />
				<Property Name="subValuePosition" />
				<Property Name="AssnNote" />
			</Property>
		</Property>
		<Property Name="RevolvingType" />
		<Property Name="NoOfRevolving" />
		<Property Name="RevolvingFqy" />
		<Property Name="ActivityCode" />
		<Property Name="MessageTypeMvGroup">
			<Term Name="TERM_LIST_TYPE">true</Term>
			<Property Name="valuePosition" />
			<Property Name="subValuePosition" />
			<Property Name="MessageType" />
			<Property Name="MsgClassNo">
				<Term Name="TERM_SEMANTIC_TYPE">A</Term>
			</Property>
			<Property Name="OvrCarrier" />
			<Property Name="AddresseeSvGroup">
				<Term Name="TERM_LIST_TYPE">true</Term>
				<Property Name="valuePosition" />
				<Property Name="subValuePosition" />
				<Property Name="Addressee" />
			</Property>
			<Property Name="SendMessage" />
		</Property>
		<Property Name="LastTraceDte" />
		<Property Name="LastTraceInfo" />
		<Property Name="LiabilityAmt" />
		<Property Name="LcAmountLocal" />
		<Property Name="Drawings" />
		<Property Name="OsusanceNo" />
		<Property Name="OsusanceVal" />
		<Property Name="OscollectNo" />
		<Property Name="OscollectVal" />
		<Property Name="DiscountNo" />
		<Property Name="DiscountVal" />
		<Property Name="NextDrawing" />
		<Property Name="PaymentAmt" />
		<Property Name="TrustRel" />
		<Property Name="TracerDate" />
		<Property Name="TracerDays" />
		<Property Name="DirectCollNo" />
		<Property Name="RiskParty">
			<Term Name="TERM_SEMANTIC_TYPE">CUS</Term>
		</Property>
		<Property Name="AmendNo" />
		<Property Name="AmendStatus" />
		<Property Name="LimitUpdate" />
		<Property Name="TotPendMvmt" />
		<Property Name="PendDecMvmt" />
		<Property Name="ChargeBaseAmt" />
		<Property Name="ConfirmationAmt" />
		<Property Name="ConfLiabAmt" />
		<Property Name="UnconfLiabAmt" />
		<Property Name="UnconfLimitRef" />
		<Property Name="LimitWithProv" />
		<Property Name="CollMatCode" />
		<Property Name="PreadvLimit" />
		<Property Name="GteeReferenceMvGroup">
			<Term Name="TERM_LIST_TYPE">true</Term>
			<Property Name="valuePosition" />
			<Property Name="subValuePosition" />
			<Property Name="GteeReference">
				<Term Name="TERM_SEMANTIC_TYPE">A</Term>
			</Property>
			<Property Name="GteeMarginAmt" />
		</Property>
		<Property Name="PartShipText" />
		<Property Name="ConfAddlInst" />
		<Property Name="PreAdvRef" />
		<Property Name="ApplicantBankMvGroup">
			<Term Name="TERM_LIST_TYPE">true</Term>
			<Property Name="valuePosition" />
			<Property Name="subValuePosition" />
			<Property Name="ApplicantBank" />
		</Property>
		<Property Name="IssBankRef" />
		<Property Name="LmtForRevolving" />
		<Property Name="CurRevolLiab" />
		<Property Name="AckAcptAmount" />
		<Property Name="730AccWithBkMvGroup">
			<Term Name="TERM_LIST_TYPE">true</Term>
			<Property Name="valuePosition" />
			<Property Name="subValuePosition" />
			<Property Name="730AccWithBk" />
		</Property>
		<Property Name="ChargesDetMvGroup">
			<Term Name="TERM_LIST_TYPE">true</Term>
			<Property Name="valuePosition" />
			<Property Name="subValuePosition" />
			<Property Name="ChargesDet" />
		</Property>
		<Property Name="730SndRcvInfMvGroup">
			<Term Name="TERM_LIST_TYPE">true</Term>
			<Property Name="valuePosition" />
			<Property Name="subValuePosition" />
			<Property Name="730SndRcvInf" />
		</Property>
		<Property Name="NegWithBankMvGroup">
			<Term Name="TERM_LIST_TYPE">true</Term>
			<Property Name="valuePosition" />
			<Property Name="subValuePosition" />
			<Property Name="NegWithBank" />
		</Property>
		<Property Name="ReimbBkChgs" />
		<Property Name="ReimbBkRef" />
		<Property Name="ReimbNarrativeMvGroup">
			<Term Name="TERM_LIST_TYPE">true</Term>
			<Property Name="valuePosition" />
			<Property Name="subValuePosition" />
			<Property Name="ReimbNarrative" />
		</Property>
		<Property Name="AckChgClaim" />
		<Property Name="AuthReimbDt" />
		<Property Name="LcOrigRate" />
		<Property Name="ApplRuleCodes" />
		<Property Name="ApplRuleDesc" />
		<Property Name="ApplRuleMt740" />
		<Property Name="DeliveryRefMvGroup">
			<Term Name="TERM_LIST_TYPE">true</Term>
			<Property Name="valuePosition" />
			<Property Name="subValuePosition" />
			<Property Name="DeliveryRef" />
		</Property>
		<Property Name="ConsolKey" />
		<Property Name="PrevConfirmInst" />
		<Property Name="ForwardContractMvGroup">
			<Term Name="TERM_LIST_TYPE">true</Term>
			<Property Name="valuePosition" />
			<Property Name="subValuePosition" />
			<Property Name="ForwardContract">
				<Term Name="TERM_SEMANTIC_TYPE">A</Term>
			</Property>
		</Property>
		<Property Name="IncoTerms" />
		<Property Name="PayTerms" />
		<Property Name="Transferable" />
		<Property Name="StandBy" />
		<Property Name="ClientRef" />
		<Property Name="ContactInfoMvGroup">
			<Term Name="TERM_LIST_TYPE">true</Term>
			<Property Name="valuePosition" />
			<Property Name="subValuePosition" />
			<Property Name="ContactInfoSvGroup">
				<Term Name="TERM_LIST_TYPE">true</Term>
				<Property Name="valuePosition" />
				<Property Name="subValuePosition" />
				<Property Name="ContactInfo" />
			</Property>
		</Property>
		<Property Name="IbLimit" />
		<Property Name="LimitBroken" />
		<Property Name="AdvBkConfirm" />
		<Property Name="IbStatus" />
		<Property Name="IbReasonMvGroup">
			<Term Name="TERM_LIST_TYPE">true</Term>
			<Property Name="valuePosition" />
			<Property Name="subValuePosition" />
			<Property Name="IbReasonSvGroup">
				<Term Name="TERM_LIST_TYPE">true</Term>
				<Property Name="valuePosition" />
				<Property Name="subValuePosition" />
				<Property Name="IbReason" />
			</Property>
		</Property>
		<Property Name="SlRefTranche" />
		<Property Name="ProductType" />
		<Property Name="BaseCcyRate" />
		<Property Name="ParticipantMvGroup">
			<Term Name="TERM_LIST_TYPE">true</Term>
			<Property Name="valuePosition" />
			<Property Name="subValuePosition" />
			<Property Name="Participant">
				<Term Name="TERM_SEMANTIC_TYPE">CUS</Term>
			</Property>
			<Property Name="PartShare" />
			<Property Name="PartAmount" />
			<Property Name="Reserved11" />
			<Property Name="Reserved12" />
		</Property>
		<Property Name="OwnPartAmount" />
		<Property Name="SyndicateCharge" />
		<Property Name="UsanceDays" />
		<Property Name="PresentationDays" />
		<Property Name="SlLinkDate" />
		<Property Name="FreeTextMsgMvGroup">
			<Term Name="TERM_LIST_TYPE">true</Term>
			<Property Name="valuePosition" />
			<Property Name="subValuePosition" />
			<Property Name="FreeTextMsgSvGroup">
				<Term Name="TERM_LIST_TYPE">true</Term>
				<Property Name="valuePosition" />
				<Property Name="subValuePosition" />
				<Property Name="FreeTextMsg" />
			</Property>
		</Property>
		<Property Name="Mt202SndRcvInfMvGroup">
			<Term Name="TERM_LIST_TYPE">true</Term>
			<Property Name="valuePosition" />
			<Property Name="subValuePosition" />
			<Property Name="Mt202SndRcvInf" />
		</Property>
		<Property Name="ProvCalcBase" />
		<Property Name="AutoExpiry" />
		<Property Name="SendMt740" />
		<Property Name="InwardMsgTypeMvGroup">
			<Term Name="TERM_LIST_TYPE">true</Term>
			<Property Name="valuePosition" />
			<Property Name="subValuePosition" />
			<Property Name="InwardMsgType" />
			<Property Name="InwardMsgRef" />
		</Property>
		<Property Name="CommCode">
			<Term Name="TERM_SEMANTIC_TYPE">A</Term>
		</Property>
		<Property Name="CommFrequency" />
		<Property Name="CommRate" />
		<Property Name="FixedCommAmt" />
		<Property Name="AccrualParam">
			<Term Name="TERM_SEMANTIC_TYPE">A</Term>
		</Property>
		<Property Name="CommAccount">
			<Term Name="TERM_SEMANTIC_TYPE">ACC</Term>
		</Property>
		<Property Name="CommExchRate" />
		<Property Name="CommClaimed" />
		<Property Name="BwdFwdKey" />
		<Property Name="CommAmount" />
		<Property Name="CommTaxAmt" />
		<Property Name="CsnCodeMvGroup">
			<Term Name="TERM_LIST_TYPE">true</Term>
			<Property Name="valuePosition" />
			<Property Name="subValuePosition" />
			<Property Name="CsnCode">
				<Term Name="TERM_SEMANTIC_TYPE">A</Term>
			</Property>
			<Property Name="UptoDays" />
			<Property Name="UptoAmtSvGroup">
				<Term Name="TERM_LIST_TYPE">true</Term>
				<Property Name="valuePosition" />
				<Property Name="subValuePosition" />
				<Property Name="UptoAmt" />
				<Property Name="CsnRate" />
				<Property Name="CsnAmt" />
			</Property>
		</Property>
		<Property Name="ReturnComm" />
		<Property Name="CommPartyChg" />
		<Property Name="ModeOfShipment" />
		<Property Name="AvailableBy" />
		<Property Name="DocumentId">
			<Term Name="TERM_SEMANTIC_TYPE">A</Term>
		</Property>
		<Property Name="Reserved6" />
		<Property Name="Reserved5" />
		<Property Name="Reserved4" />
		<Property Name="Reserved3" />
		<Property Name="Reserved2" />
		<Property Name="Reserved1" />
		<Property Name="StmtEntryNoMvGroup">
			<Term Name="TERM_LIST_TYPE">true</Term>
			<Property Name="valuePosition" />
			<Property Name="subValuePosition" />
			<Property Name="StmtEntryNo" />
		</Property>
		<Property Name="OverrideMvGroup">
			<Term Name="TERM_LIST_TYPE">true</Term>
			<Property Name="valuePosition" />
			<Property Name="subValuePosition" />
			<Property Name="Override" />
		</Property>
		<Property Name="RecordStatus" />
		<Property Name="CurrNo" />
		<Property Name="InputterMvGroup">
			<Term Name="TERM_LIST_TYPE">true</Term>
			<Property Name="valuePosition" />
			<Property Name="subValuePosition" />
			<Property Name="Inputter" />
		</Property>
		<Property Name="DateTimeMvGroup">
			<Term Name="TERM_LIST_TYPE">true</Term>
			<Property Name="valuePosition" />
			<Property Name="subValuePosition" />
			<Property Name="DateTime" />
		</Property>
		<Property Name="Authoriser" />
		<Property Name="CoCode">
			<Term Name="TERM_SEMANTIC_TYPE">A</Term>
		</Property>
		<Property Name="DeptCode" />
		<Property Name="AuditorCode" />
		<Property Name="AuditDateTime" />
		<Property Name="InMsgRef" />
		<Property Name="InMsgType" />
		<Property Name="TransType" />
		<Property Name="Prodccy" />
		<Property Name="Residence" />
		<Property Name="InterestBasis" />
		<Property Name="SourceId" />
		<Property Name="SourceFile" />
		<Property Name="CustomerNo" />
		<Property Name="Sector" />
		<Property Name="Industry" />
		<Property Name="Target" />
		<Property Name="Category" />
		<Property Name="RiskCountry" />
		<Property Name="LcTypeExp" />
		<Property Name="LcTypeTr" />
		<Property Name="LcTypeDoc" />
		<Property Name="LcTypeClCr" />
		<Property Name="LcTypeClCol" />
		<Property Name="Id" />
	</Entity>
</Metadata>
